fastapi_frame_stream/__init__.py
fastapi_frame_stream/streamer.py
fastapi_frame_stream-0.1.1.dist-info/LICENSE
fastapi_frame_stream-0.1.1.dist-info/METADATA
fastapi_frame_stream-0.1.1.dist-info/WHEEL
fastapi_frame_stream-0.1.1.dist-info/top_level.txt
fastapi_frame_stream-0.1.1.dist-info/RECORD
