Metadata-Version: 2.1
Name: fastapi-frame-stream
Version: 0.1.1
Summary: Package to easily stream individual frames (MJPEG) using FastAPI
Home-page: https://github.com/TiagoPrata/fastapi-frame-stream
Author: Tiago Prata
Author-email: prataaa@hotmail.com
Classifier: Programming Language :: Python :: 3
Classifier: License :: OSI Approved :: MIT License
Classifier: Operating System :: OS Independent
Classifier: Intended Audience :: Developers
Requires-Python: >=3.7
License-File: LICENSE
Requires-Dist: imutils
Requires-Dist: opencv-python
Requires-Dist: python-multipart
